clearbox_preprocessor/__init__.py
clearbox_preprocessor/preprocessor.py
clearbox_preprocessor/utils/__init__.py
clearbox_preprocessor/utils/categorical_transformer.py
clearbox_preprocessor/utils/datetime_transformer.py
clearbox_preprocessor/utils/numerical_transformer.py
clearbox_preprocessor-0.12.7.dist-info/LICENSE
clearbox_preprocessor-0.12.7.dist-info/METADATA
clearbox_preprocessor-0.12.7.dist-info/WHEEL
clearbox_preprocessor-0.12.7.dist-info/top_level.txt
clearbox_preprocessor-0.12.7.dist-info/RECORD
