Metadata-Version: 2.1
Name: clearbox-preprocessor
Version: 0.12.7
Summary: A fast polars based data pre-processor for ML datasets
Home-page: https://github.com/Clearbox-AI/preprocessor
Author: Dario Brunelli
Author-email: dario@clearbox.ai
Requires-Python: >3.9
License-File: LICENSE
Requires-Dist: numpy<2.0.0
Requires-Dist: pandas<=2.2.3
Requires-Dist: scikit-learn
Requires-Dist: scipy<=1.14
Requires-Dist: polars<=1.17.1
Requires-Dist: tsfresh==0.20.3
Requires-Dist: sphinx
Requires-Dist: myst-parser
Requires-Dist: sphinxemoji
Requires-Dist: numpydoc
Requires-Dist: sphinx-rtd-theme
Provides-Extra: dev
Requires-Dist: check-manifest; extra == "dev"
Requires-Dist: pytest>3.9; extra == "dev"
Provides-Extra: test
Requires-Dist: coverage; extra == "test"
